ethminer_supervisor/__init__.py
ethminer_supervisor/cli.py
ethminer_supervisor/util.py
ethminer_supervisor-1.1.0.dist-info/DESCRIPTION.rst
ethminer_supervisor-1.1.0.dist-info/METADATA
ethminer_supervisor-1.1.0.dist-info/RECORD
ethminer_supervisor-1.1.0.dist-info/WHEEL
ethminer_supervisor-1.1.0.dist-info/entry_points.txt
ethminer_supervisor-1.1.0.dist-info/metadata.json
ethminer_supervisor-1.1.0.dist-info/top_level.txt
ethminer_supervisor-1.1.0.dist-info/zip-safe
tests/__init__.py
tests/test_util.py
