Metadata-Version: 2.0
Name: ethminer-supervisor
Version: 1.1.0
Summary: Supervise ethminer daemon and restart process or machine when appropriate
Home-page: https://github.com/narfman0/ethminer_supervisor
Author: Jon Robison
Author-email: narfman0@gmail.com
License: MIT license
Keywords: ethminer_supervisor ethereum
Platform: UNKNOWN
Classifier: Development Status :: 4 - Beta
Classifier: Intended Audience :: Developers
Classifier: License :: OSI Approved :: MIT License
Classifier: Natural Language :: English
Classifier: Programming Language :: Python :: 2
Classifier: Programming Language :: Python :: 2.7
Classifier: Programming Language :: Python :: 3
Classifier: Programming Language :: Python :: 3.6
